config/parameters/etlObjects.json
config/parameters/datasources/csvFileDS.json
config/parameters/datasources/excelFileDS.json
config/parameters/datasources/odbcDS.json
config/parameters/datasources/piDS.json
config/parameters/datasources/sapRfcTableDS.json
config/parameters/datasources/xesFileDS.json
config/parameters/transformers/concatTR.json
config/parameters/transformers/extractstrTR.json
config/parameters/transformers/jinjaTR.json
config/parameters/transformers/joinTR.json
config/parameters/transformers/lookupTR.json
config/parameters/transformers/profileTR.json
config/parameters/transformers/renamecolTR.json
config/templates/profile.html
pipelite/__init__.py
pipelite/constants.py
pipelite/pipelineProcess.py
pipelite/plConfig.py
pipelite/plDataset.py
pipelite/plDatasets.py
pipelite/plObject.py
pipelite/baseobjs/BODataSource.py
pipelite/baseobjs/BOPipeline.py
pipelite/baseobjs/BOTransformer.py
pipelite/baseobjs/__init__.py
pipelite/baseobjs/plBaseObject.py
pipelite/config/__init__.py
pipelite/config/cmdLineConfig.py
pipelite/config/plConfig.py
pipelite/datasources/__init__.py
pipelite/datasources/csvFileDS.py
pipelite/datasources/excelFileDS.py
pipelite/datasources/folderDS.py
pipelite/datasources/odbcDS.py
pipelite/datasources/piDS.py
pipelite/datasources/sapRfcTableDS.py
pipelite/datasources/xesFileDS.py
pipelite/datasources/abbyypi/__init__.py
pipelite/datasources/abbyypi/piApiRepositoryWrapper.py
pipelite/datasources/abbyypi/piRepository.py
pipelite/datasources/abbyypi/repConfig.py
pipelite/datasources/abbyypi/uploadConfig.py
pipelite/datasources/sql/sqlTemplate.py
pipelite/pipelines/__init__.py
pipelite/pipelines/sequentialPL.py
pipelite/pipelines/management/plNode.py
pipelite/pipelines/management/plTree.py
pipelite/transformers/concatTR.py
pipelite/transformers/extractstrTR.py
pipelite/transformers/jinjaTR.py
pipelite/transformers/joinTR.py
pipelite/transformers/lookupTR.py
pipelite/transformers/passthroughTR.py
pipelite/transformers/profileTR.py
pipelite-0.1.9.1.dist-info/LICENSE
pipelite-0.1.9.1.dist-info/METADATA
pipelite-0.1.9.1.dist-info/WHEEL
pipelite-0.1.9.1.dist-info/entry_points.txt
pipelite-0.1.9.1.dist-info/top_level.txt
pipelite-0.1.9.1.dist-info/RECORD
