Metadata-Version: 2.1
Name: pipelite
Version: 0.1.9.1
Summary: This solution build by design (configuration) simple of complex Data Pipelines
Author-email: datacorner <admin@datacorner.fr>
License: MIT License
Project-URL: Bug Tracker, https://github.com/datacorner/pipelite/issues
Project-URL: Homepage, https://github.com/datacorner/pipelite/wiki
Classifier: Development Status :: 3 - Alpha
Classifier: Operating System :: OS Independent
Classifier: Environment :: Console
Classifier: Programming Language :: Python :: 3.10
Requires-Python: >=3.10
License-File: LICENSE
Requires-Dist: pandas ==2.0.3
Requires-Dist: openpyxl ==3.1.2
Requires-Dist: pyodbc ==4.0.39
Requires-Dist: pyrfc ==3.1
Requires-Dist: requests ==2.31.0
Requires-Dist: xmltodict ==0.13.0
Requires-Dist: jsonpath-ng ==1.6.0
Requires-Dist: jsonschema ==4.19.1
Requires-Dist: Jinja2 ==3.1.2
